ipycontrols7/__init__.py
ipycontrols7/_frontend.py
ipycontrols7/_version.py
ipycontrols7/labextension/build_log.json
ipycontrols7/labextension/package.json
ipycontrols7/labextension/static/lib_index_js.96317fc3813c28407742.js
ipycontrols7/labextension/static/lib_index_js.96317fc3813c28407742.js.map
ipycontrols7/labextension/static/lib_plugin_js-data_image_svg_xml_base64_PD94bWwgdmVyc2lvbj0iMS4wIiBlbmNvZGluZz0idXRmLTgiPz4KP-a6bae6.c5d30f52400bddd7187f.js
ipycontrols7/labextension/static/lib_plugin_js-data_image_svg_xml_base64_PD94bWwgdmVyc2lvbj0iMS4wIiBlbmNvZGluZz0idXRmLTgiPz4KP-a6bae6.c5d30f52400bddd7187f.js.map
ipycontrols7/labextension/static/node_modules_jupyter-controls7_lib_version_js.543a9a7bfe2d9e5b2eab.js
ipycontrols7/labextension/static/node_modules_jupyter-controls7_lib_version_js.543a9a7bfe2d9e5b2eab.js.map
ipycontrols7/labextension/static/remoteEntry.171fda354f9633a779e2.js
ipycontrols7/labextension/static/remoteEntry.171fda354f9633a779e2.js.map
ipycontrols7/labextension/static/style.js
ipycontrols7/labextension/static/vendors-node_modules_jupyter-controls7_lib_index_js.b4bd8a96fd72d4544bc6.js
ipycontrols7/labextension/static/vendors-node_modules_jupyter-controls7_lib_index_js.b4bd8a96fd72d4544bc6.js.map
ipycontrols7/labextension/static/vendors-node_modules_jupyter-controls7_lib_version_js-node_modules_jupyter-controls7_css_widg-8c6813.90f0ab5ed4426e1e629c.js
ipycontrols7/labextension/static/vendors-node_modules_jupyter-controls7_lib_version_js-node_modules_jupyter-controls7_css_widg-8c6813.90f0ab5ed4426e1e629c.js.map
ipycontrols7/nbextension/extension.js
ipycontrols7/nbextension/index.js
ipycontrols7/nbextension/index.js.map
ipycontrols7/tests/__init__.py
ipycontrols7/tests/conftest.py
ipycontrols7/tests/test_example.py
ipycontrols7/tests/test_nbextension_path.py
ipycontrols7-0.1.0.dev0.data/data/share/jupyter/labextensions/ipycontrols7/build_log.json
ipycontrols7-0.1.0.dev0.data/data/share/jupyter/labextensions/ipycontrols7/package.json
ipycontrols7-0.1.0.dev0.dist-info/METADATA
ipycontrols7-0.1.0.dev0.dist-info/WHEEL
ipycontrols7-0.1.0.dev0.dist-info/licenses/LICENSE.txt
ipycontrols7-0.1.0.dev0.dist-info/RECORD
